cjm_text_plugin_nltk/__init__.py
cjm_text_plugin_nltk/_modidx.py
cjm_text_plugin_nltk/meta.py
cjm_text_plugin_nltk/plugin.py
cjm_text_plugin_nltk-0.0.1.dist-info/licenses/LICENSE
cjm_text_plugin_nltk-0.0.1.dist-info/METADATA
cjm_text_plugin_nltk-0.0.1.dist-info/WHEEL
cjm_text_plugin_nltk-0.0.1.dist-info/entry_points.txt
cjm_text_plugin_nltk-0.0.1.dist-info/top_level.txt
cjm_text_plugin_nltk-0.0.1.dist-info/RECORD
