Metadata-Version: 2.4
Name: cjm-text-plugin-nltk
Version: 0.0.1
Summary: A local, NLTK-based text processing worker for the cjm-plugin-system that provides sentence splitting and tokenization with character-level span tracking.
Home-page: https://github.com/cj-mills/cjm-text-plugin-nltk
Author: Christian J. Mills
Author-email: 9126128+cj-mills@users.noreply.github.com
License: Apache-2.0
Keywords: nbdev jupyter notebook python
Classifier: Development Status :: 4 - Beta
Classifier: Intended Audience :: Developers
Classifier: Natural Language :: English
Classifier: Programming Language :: Python :: 3.11
Classifier: Programming Language :: Python :: 3.12
Classifier: Programming Language :: Python :: 3.13
Requires-Python: >=3.11
License-File: LICENSE
Requires-Dist: cjm_text_plugin_system
Requires-Dist: nltk
Provides-Extra: dev
Dynamic: author
Dynamic: author-email
Dynamic: classifier
Dynamic: description
Dynamic: description-content-type
Dynamic: home-page
Dynamic: keywords
Dynamic: license
Dynamic: license-file
Dynamic: provides-extra
Dynamic: requires-dist
Dynamic: requires-python
Dynamic: summary
